task1/gray2bcd.vhdl
library IEEE;
use IEEE.STD_LOGIC_1164.ALL;
    entity gray2bcd_artyshevskyi is 
        Port (
            a : in std_logic;
            b : in std_logic;
            c : in std_logic;
            bcd : out std_logic_vector (2 downto 0)
        );
    end gray2bcd_artyshevskyi;
    
    architecture Behavioral of gray2bcd_artyshevskyi is

        begin
            belt : process (a, b, c)
                variable gray : std_logic_vector (2 downto 0);
            begin
                gray := a&b&c;
                if gray="000" then
                    bcd<="000";
                elsif gray="001" then
                    bcd<="001";
                elsif gray="011" then
                    bcd<="010";   
                elsif gray="010" then
                    bcd<="011";
                elsif gray="110" then
                    bcd<="100";
                elsif gray="111" then
                    bcd<="101";
                elsif gray="101" then
                    bcd<="110";
                elsif gray="100" then
                    bcd<="111";                                                                     
                end if;
            end process belt;
end Behavioral;

task1/gray2bcdtb.vhdl
library ieee;
use ieee.std_logic_1164.ALL;

entity gray2bcdtb is
end gray2bcdtb;

architecture behavior of gray2bcdtb is
    component gray2bcd_artyshevskyi
        Port (
            a : in std_logic;
            b : in std_logic;
            c : in std_logic;
            bcd : out std_logic_vector (2 downto 0)
        );
    end component;

    signal a : std_logic :='0';
    signal b : std_logic :='0';
    signal c : std_logic :='0';

    signal bcd : std_logic_vector (2 downto 0);

    begin
        uut: gray2bcd_artyshevskyi PORT MAP (
            a=>a,
            b=>b,
            c=>c,
            bcd => bcd
        );

        stim_process: process
        begin
            -- wait for 100 ns;
            
            a<='0';
            b<='0';
            c<='0';
            wait for 10 ns;

            a<='0';
            b<='0';
            c<='1';
            wait for 10 ns;

            a<='0';
            b<='1';
            c<='1';
            wait for 10 ns;

            a<='0';
            b<='1';
            c<='0';
            wait for 10 ns;

            a<='1';
            b<='1';
            c<='0';
            wait for 10 ns;

            a<='1';
            b<='1';
            c<='1';
            wait for 10 ns;

            a<='1';
            b<='0';
            c<='1';
            wait for 10 ns;

            a<='1';
            b<='0';
            c<='0';
            wait for 10 ns;
            wait;
        end process;
    end;

task1/gray2bcd.vcd
$date
  Thu Nov 14 15:14:00 2024
$end
$version
  GHDL v0
$end
$timescale
  1 fs
$end
$scope module standard $end
$upscope $end
$scope module std_logic_1164 $end
$upscope $end
$scope module gray2bcdtb $end
$var reg 1 ! a $end
$var reg 1 " b $end
$var reg 1 # c $end
$var reg 3 $ bcd[2:0] $end
$scope module uut $end
$var reg 1 % a $end
$var reg 1 & b $end
$var reg 1 ' c $end
$var reg 3 ( bcd[2:0] $end
$upscope $end
$upscope $end
$enddefinitions $end
#0
0!
0"
0#
b000 $
0%
0&
0'
b000 (
#10000000
1#
b001 $
1'
b001 (
#20000000
1"
b010 $
1&
b010 (
#30000000
0#
b011 $
0'
b011 (
#40000000
1!
b100 $
1%
b100 (
#50000000
1#
b101 $
1'
b101 (
#60000000
0"
b110 $
0&
b110 (
#70000000
0#
b111 $
0'
b111 (
