task2/belt.vhdl
library IEEE;
use IEEE.STD_LOGIC_1164.ALL;
    entity belt_artyshevskyi is 
        Port (
            s1 : in std_logic;--\
            s2 : in std_logic;-- \
            s3 : in std_logic;-- / sensors
            s4 : in std_logic;--/
            sw : in std_logic;-- stop/start switch
            r : out std_logic;-- rotate anti clock wise
            t: out std_logic -- turn over
        );
    end belt_artyshevskyi;
    
    architecture Behavioral of belt_artyshevskyi is

        begin
            belt : process (sw, s1, s2, s3, s4)
                variable sensors : std_logic_vector (4 downto 0);
            begin
                sensors := sw&s1&s2&s3&s4;
                if (sensors="01000") then
                    r<='1';
                    t<='1';
                elsif (sensors="00100") then
                    r<='1';
                    t<='0';
                elsif (sensors="00010") then
                    r<='0';
                    t<='0';  
                elsif (sensors="00001") then
                    r<='0';
                    t<='1';
                else
                    r<='Z';
                    t<='Z';
                end if;
            end process belt;
end Behavioral;

task2/belttb.vhdl
library ieee;
use ieee.std_logic_1164.ALL;

entity belttb is
end belttb;

architecture behavior of belttb is
    component belt_artyshevskyi
        Port (
            s1 : in std_logic;--\
            s2 : in std_logic;-- \
            s3 : in std_logic;-- / sensors
            s4 : in std_logic;--/
            sw : in std_logic;-- stop/start switch
            r : out std_logic;-- rotate anti clock wise
            t: out std_logic -- turn over
        );
    end component;

    signal s1 : std_logic := '0';
    signal s2 : std_logic := '0';
    signal s3 : std_logic := '0';
    signal s4 : std_logic := '0';
    signal sw : std_logic := '0';

    signal r : std_logic;
    signal t : std_logic;

    begin
        uut: belt_artyshevskyi PORT MAP (
            sw=>sw,
            s1=>s1,
            s2=>s2,
            s3=>s3,
            s4=>s4,
            r=>r,
            t=>t
        );

        stim_process: process
        begin
            wait for 100 ns;

            sw<='0';

                s1<='1';
            wait for 10 ns;
                s1<='0';
                s2<='1';
            wait for 10 ns;
                s2<='0';
                s3<='1';
            wait for 10 ns;
                s3<='0';
                s4<='1';
            wait for 10 ns;
                s4<='0';

            sw<='1';
                s1<='1';
            wait for 10 ns;
                s1<='0';
                s2<='1';
            wait for 10 ns;
                s2<='0';
                s3<='1';
            wait for 10 ns;
                s3<='0';
                s4<='1';
            wait for 10 ns;
                sw<='0';
                s4<='0';

            wait for 40 ns;
                s1<='0';
                s2<='1';
                s3<='1';
                s4<='1';
            wait for 10 ns;
                s1<='0';
                s2<='0';
                s3<='0';
                s4<='0';
            wait;

        end process;
    end;

task2/belt.vcd
$date
  Sun Nov 10 19:35:47 2024
$end
$version
  GHDL v0
$end
$timescale
  1 fs
$end
$scope module standard $end
$upscope $end
$scope module std_logic_1164 $end
$upscope $end
$scope module belttb $end
$var reg 1 ! s1 $end
$var reg 1 " s2 $end
$var reg 1 # s3 $end
$var reg 1 $ s4 $end
$var reg 1 % sw $end
$var reg 1 & r $end
$var reg 1 ' t $end
$scope module uut $end
$var reg 1 ( s1 $end
$var reg 1 ) s2 $end
$var reg 1 * s3 $end
$var reg 1 + s4 $end
$var reg 1 , sw $end
$var reg 1 - r $end
$var reg 1 . t $end
$upscope $end
$upscope $end
$enddefinitions $end
#0
0!
0"
0#
0$
0%
Z&
Z'
0(
0)
0*
0+
0,
Z-
Z.
#100000000
1!
1&
1'
1(
1-
1.
#110000000
0!
1"
0'
0(
1)
0.
#120000000
0"
1#
0&
0)
1*
0-
#130000000
0#
1$
1'
0*
1+
1.
#140000000
1!
0$
1%
Z&
Z'
1(
0+
1,
Z-
Z.
#150000000
0!
1"
0(
1)
#160000000
0"
1#
0)
1*
#170000000
0#
1$
0*
1+
#180000000
0$
0%
0+
0,
#220000000
1"
1#
1$
1)
1*
1+
#230000000
0"
0#
0$
0)
0*
0+
